ddn_evo/__info__.py
ddn_evo/__init__.py
ddn_evo/discrete_distribution.py
ddn_evo/sddn_utils.py
ddn_evo/vis_tree_latent_recursively.py
ddn_evo-0.3.0.dist-info/METADATA
ddn_evo-0.3.0.dist-info/WHEEL
ddn_evo-0.3.0.dist-info/top_level.txt
ddn_evo-0.3.0.dist-info/RECORD
