Metadata-Version: 2.4
Name: ddn_evo
Version: 0.3.0
Summary: Discrete Distribution Networks with Evolutionary Algorithms
Home-page: https://github.com/EmreDinc10/ddn_evo
Author: Emre Dinc
Author-email: emredinc09@gmail.com
Classifier: Topic :: Software Development :: Libraries :: Python Modules
Classifier: Programming Language :: Python :: 3
Classifier: License :: OSI Approved :: MIT License
Classifier: License :: OSI Approved :: Apache Software License
Classifier: Operating System :: OS Independent
Requires-Dist: boxx
Dynamic: author
Dynamic: author-email
Dynamic: classifier
Dynamic: description
Dynamic: description-content-type
Dynamic: home-page
Dynamic: requires-dist
Dynamic: summary
